nats_pkg/__init__.py
nats_pkg/_handler.py
nats_pkg/nats_client.py
nats_python_client-0.0.2.dist-info/LICENCE
nats_python_client-0.0.2.dist-info/METADATA
nats_python_client-0.0.2.dist-info/WHEEL
nats_python_client-0.0.2.dist-info/top_level.txt
nats_python_client-0.0.2.dist-info/RECORD
